dooit/__init__.py
dooit/__main__.py
dooit/api/__init__.py
dooit/api/_vars.py
dooit/api/exceptions.py
dooit/api/hooks/fix_hooks.py
dooit/api/hooks/update_hooks.py
dooit/api/hooks/validation_hooks.py
dooit/api/manager.py
dooit/api/model.py
dooit/api/theme.py
dooit/api/todo.py
dooit/api/workspace.py
dooit/backport/migrate_from_v2.py
dooit/ui/__init__.py
dooit/ui/api/__init__.py
dooit/ui/api/api_components/__init__.py
dooit/ui/api/api_components/_base.py
dooit/ui/api/api_components/bar.py
dooit/ui/api/api_components/dashboard.py
dooit/ui/api/api_components/formatters/__init__.py
dooit/ui/api/api_components/formatters/_decorators.py
dooit/ui/api/api_components/formatters/_model_formatter_base.py
dooit/ui/api/api_components/formatters/formatter.py
dooit/ui/api/api_components/formatters/formatter_store.py
dooit/ui/api/api_components/formatters/model_formatters.py
dooit/ui/api/api_components/keys.py
dooit/ui/api/api_components/layout.py
dooit/ui/api/api_components/vars.py
dooit/ui/api/dooit_api.py
dooit/ui/api/event_handlers.py
dooit/ui/api/events/__init__.py
dooit/ui/api/events/events.py
dooit/ui/api/loader.py
dooit/ui/api/plug.py
dooit/ui/api/widgets.py
dooit/ui/screens/__init__.py
dooit/ui/screens/base.py
dooit/ui/screens/help.py
dooit/ui/screens/index.py
dooit/ui/styles.tcss
dooit/ui/tui.py
dooit/ui/widgets/__init__.py
dooit/ui/widgets/aligner.py
dooit/ui/widgets/bars/__init__.py
dooit/ui/widgets/bars/_base.py
dooit/ui/widgets/bars/bar_switcher.py
dooit/ui/widgets/bars/confirm_bar/__init__.py
dooit/ui/widgets/bars/confirm_bar/bar.py
dooit/ui/widgets/bars/notification_bar/__init__.py
dooit/ui/widgets/bars/notification_bar/bar.py
dooit/ui/widgets/bars/search_bar/__init__.py
dooit/ui/widgets/bars/search_bar/bar.py
dooit/ui/widgets/bars/sort_bar/__init__.py
dooit/ui/widgets/bars/sort_bar/bar.py
dooit/ui/widgets/bars/status_bar/__init__.py
dooit/ui/widgets/bars/status_bar/bar.py
dooit/ui/widgets/bars/status_bar/bar_widget.py
dooit/ui/widgets/base.py
dooit-3.3.3.dist-info/LICENSE
dooit-3.3.3.dist-info/METADATA
dooit-3.3.3.dist-info/WHEEL
dooit-3.3.3.dist-info/entry_points.txt
dooit-3.3.3.dist-info/RECORD
