Metadata-Version: 2.3
Name: dooit
Version: 3.3.3
Summary: A TUI Todo Manager
License: MIT
Author: kraanzu
Author-email: kraanzu@gmail.com
Maintainer: kraanzu
Maintainer-email: kraanzu@gmail.com
Requires-Python: >=3.9,<4.0
Classifier: License :: OSI Approved :: MIT License
Classifier: Programming Language :: Python :: 3
Classifier: Programming Language :: Python :: 3.9
Classifier: Programming Language :: Python :: 3.10
Classifier: Programming Language :: Python :: 3.11
Classifier: Programming Language :: Python :: 3.12
Classifier: Programming Language :: Python :: 3.13
Requires-Dist: click (>=8.1.7,<9.0.0)
Requires-Dist: platformdirs (>=4.3.6,<5.0.0)
Requires-Dist: pyperclip (>=1.9.0,<2.0.0)
Requires-Dist: python-dateutil (>=2.9.0.post0,<3.0.0)
Requires-Dist: pyyaml (>=6.0.2,<7.0.0)
Requires-Dist: sqlalchemy (>=2.0.36,<3.0.0)
Requires-Dist: textual (>=5.3.0,<6.0.0)
Requires-Dist: tzlocal (>=5.2,<6.0)
Project-URL: Homepage, https://github.com/dooit-org/dooit
Project-URL: Repository, https://github.com/dooit-org/dooit
